autoquiz/__init__.py
autoquiz/cases/__init__.py
autoquiz/cases/insert_note.py
autoquiz/dtos/__init__.py
autoquiz/dtos/recievenote.py
autoquiz/entities/__init__.py
autoquiz/entities/note.py
autoquiz/noteintroducer/__init__.py
autoquiz/noteintroducer/agents/__init__.py
autoquiz/noteintroducer/agents/memory_supported_formats_storage.py
autoquiz/noteintroducer/agents/note_reader_config.py
autoquiz/noteintroducer/data/default_formats.toml
autoquiz/noteintroducer/format_selector.py
autoquiz/noteintroducer/note_reader.py
autoquiz/noteintroducer/protocols/__init__.py
autoquiz/noteintroducer/protocols/note_reader_config.py
autoquiz/noteintroducer/protocols/supported_formats_storage.py
autoquiz-0.1.0.dist-info/METADATA
autoquiz-0.1.0.dist-info/WHEEL
autoquiz-0.1.0.dist-info/RECORD
